nervous_sensors/Makefile
nervous_sensors/__init__.py
nervous_sensors/async_manager.py
nervous_sensors/cli.py
nervous_sensors/cli_listener.py
nervous_sensors/codec.py
nervous_sensors/connection_manager.py
nervous_sensors/data_manager.py
nervous_sensors/folder_manager.py
nervous_sensors/gui.py
nervous_sensors/gui_manager.py
nervous_sensors/icon.png
nervous_sensors/lsl_manager.py
nervous_sensors/nervous_ecg.py
nervous_sensors/nervous_eda.py
nervous_sensors/nervous_hr.py
nervous_sensors/nervous_scr.py
nervous_sensors/nervous_sensor.py
nervous_sensors/nervous_virtual.py
nervous_sensors/pb2.py
nervous_sensors/protocol/.gitignore
nervous_sensors/protocol/README.md
nervous_sensors/protocol/renforce.options
nervous_sensors/protocol/renforce.proto
nervous_sensors/utils.py
nervous_sensors/viewer.py
nervous_sensors-0.2.2.dist-info/LICENSE.md
nervous_sensors-0.2.2.dist-info/METADATA
nervous_sensors-0.2.2.dist-info/WHEEL
nervous_sensors-0.2.2.dist-info/entry_points.txt
nervous_sensors-0.2.2.dist-info/RECORD
