Metadata-Version: 2.3
Name: nervous-sensors
Version: 0.2.2
Summary: Python backend for connection to ECG and EDA sensors from the Lyon Institute of Nanotechnology (INL)
License: MIT
Author: Bertrand Massot
Author-email: bertrand.massot@insa-lyon.fr
Requires-Python: >=3.11,<3.14
Classifier: License :: OSI Approved :: MIT License
Classifier: Programming Language :: Python :: 3
Classifier: Programming Language :: Python :: 3.11
Classifier: Programming Language :: Python :: 3.12
Classifier: Programming Language :: Python :: 3.13
Requires-Dist: aioconsole (>=0.7.1)
Requires-Dist: bleak (>=0.22.2)
Requires-Dist: click (>=8.1.7)
Requires-Dist: cobs (>=1.2.0)
Requires-Dist: dash (>=2.16.1)
Requires-Dist: dash_bootstrap_components (>=1.6.0)
Requires-Dist: nervous-analytics (>=0.3.4)
Requires-Dist: numpy (>=1.26.4)
Requires-Dist: pandas (>=2.2.1)
Requires-Dist: plotly (>=5.22.0)
Requires-Dist: protobuf (>=4.23.4)
Requires-Dist: pylsl (>=1.16.2)
Project-URL: Repository, https://github.com/sensors-inl/Nervous-Sensors
